knowt/ann.py
knowt/ask.py
knowt/constants.py
knowt/embedding.py
knowt/llm.py
knowt/memmap.py
knowt/scrape_hpr.py
knowt/search.py
knowt/speed_test.py
knowt/together.py
knowt/validation.py
knowt-0.1.4.dist-info/LICENSE.md
knowt-0.1.4.dist-info/METADATA
knowt-0.1.4.dist-info/WHEEL
knowt-0.1.4.dist-info/entry_points.txt
knowt-0.1.4.dist-info/top_level.txt
knowt-0.1.4.dist-info/RECORD
