Metadata-Version: 2.1
Name: knowt
Version: 0.1.4
Summary: Private, personalized searchable knowledge base, from your own notes.
Author-email: Hobson Lane <git@totalgood.com>, Ethan Cavill <ethancavill@gmail.com>
License: GPLv3+
Keywords: NLP,LLM,vector-search,ANN,numpy,search,semantic search,RAG,personal assistant,command line
Classifier: Programming Language :: Python :: 3
Classifier: License :: OSI Approved :: GNU General Public License v3 or later (GPLv3+)
Requires-Python: >=3.10
License-File: LICENSE.md
Requires-Dist: ipython
Requires-Dist: joblib <1.4,>=1.3.2
Requires-Dist: jsonlines
Requires-Dist: jupyter
Requires-Dist: jupyter-console
Requires-Dist: numpy <1.27,>=1.26.2
Requires-Dist: pandas <2.3,>=2.2.0
Requires-Dist: scikit-learn <1.4,>=1.3.2
Requires-Dist: spacy <3.8,>=3.7.2
Provides-Extra: all
Requires-Dist: test ; extra == 'all'
Requires-Dist: ann ; extra == 'all'
Requires-Dist: llm ; extra == 'all'
Requires-Dist: spacy ; extra == 'all'
Requires-Dist: vaex ; extra == 'all'
Requires-Dist: dask ; extra == 'all'
Requires-Dist: transformers ; extra == 'all'
Provides-Extra: ann
Requires-Dist: py-lsh ; extra == 'ann'
Provides-Extra: dask
Requires-Dist: dask ; extra == 'dask'
Provides-Extra: llm
Requires-Dist: python-dotenv ; extra == 'llm'
Requires-Dist: openai ; extra == 'llm'
Provides-Extra: test
Requires-Dist: pytest ; extra == 'test'
Requires-Dist: black ; extra == 'test'
Requires-Dist: twine ; extra == 'test'
Requires-Dist: pip ; extra == 'test'
Requires-Dist: build ; extra == 'test'
Requires-Dist: wheel ; extra == 'test'
Provides-Extra: transformers
Requires-Dist: sentence-transformers <2.3,>=2.2.2 ; extra == 'transformers'
Provides-Extra: vaex
Requires-Dist: vaex <4.18,>=4.17.0 ; extra == 'vaex'
